wallabag/__init__.py
wallabag/config.py
wallabag/configurator.py
wallabag/entry.py
wallabag/format_type.py
wallabag/wallabag.py
wallabag/wclick.py
wallabag/api/__init__.py
wallabag/api/add_entry.py
wallabag/api/add_tag_to_entry.py
wallabag/api/api.py
wallabag/api/api_token.py
wallabag/api/delete_annotation.py
wallabag/api/delete_entry.py
wallabag/api/delete_tag_by_id.py
wallabag/api/delete_tag_from_entry.py
wallabag/api/delete_tags_by_label.py
wallabag/api/entry_exists.py
wallabag/api/export_entry.py
wallabag/api/get_api_version.py
wallabag/api/get_entry.py
wallabag/api/get_list_entries.py
wallabag/api/get_tags.py
wallabag/api/get_tags_for_entry.py
wallabag/api/update_entry.py
wallabag/commands/__init__.py
wallabag/commands/add.py
wallabag/commands/anno.py
wallabag/commands/command.py
wallabag/commands/delete.py
wallabag/commands/delete_by_tags.py
wallabag/commands/export.py
wallabag/commands/info.py
wallabag/commands/list.py
wallabag/commands/open.py
wallabag/commands/params.py
wallabag/commands/show.py
wallabag/commands/tags.py
wallabag/commands/tags_param.py
wallabag/commands/update.py
wallabag/commands/update_by_tags.py
wallabag/export/__init__.py
wallabag/export/export.py
wallabag/export/export_cli.py
wallabag/export/export_factory.py
wallabag/export/export_html.py
wallabag/export/export_md.py
wallabag_client-1.8.11.dist-info/licenses/LICENSE
wallabag_client-1.8.11.dist-info/METADATA
wallabag_client-1.8.11.dist-info/WHEEL
wallabag_client-1.8.11.dist-info/entry_points.txt
wallabag_client-1.8.11.dist-info/top_level.txt
wallabag_client-1.8.11.dist-info/RECORD
