Metadata-Version: 2.4
Name: wallabag-client
Version: 1.8.11
Summary: A command-line client for the self-hosted `read-it-later` app Wallabag
Home-page: https://github.com/artur-shaik/wallabag-client
Author: Artur Shaik
Author-email: artur@shaik.link
Classifier: Programming Language :: Python :: 3
Classifier: License :: OSI Approved :: MIT License
Classifier: Operating System :: OS Independent
Requires-Python: >=3.6
License-File: LICENSE
Requires-Dist: beautifulsoup4>=4.9.1
Requires-Dist: pycryptodome>=3.9.8
Requires-Dist: requests>=2.11.1
Requires-Dist: click>=8.0
Requires-Dist: yaspin
Requires-Dist: click_repl>=0.2.0
Requires-Dist: pyxdg
Requires-Dist: colorama>=0.4.3
Requires-Dist: delorean
Requires-Dist: humanize
Requires-Dist: lxml
Requires-Dist: tzlocal
Requires-Dist: tabulate
Requires-Dist: packaging
Requires-Dist: markdownify
Dynamic: author
Dynamic: author-email
Dynamic: classifier
Dynamic: description
Dynamic: description-content-type
Dynamic: home-page
Dynamic: license-file
Dynamic: requires-dist
Dynamic: requires-python
Dynamic: summary
